AICORELibrary/__init__.py
AICORELibrary/clickhouse/__init__.py
AICORELibrary/clickhouse/__version__.py
AICORELibrary/clickhouse/common.py
AICORELibrary/clickhouse/entry_points.py
AICORELibrary/clickhouse/json_impl.py
AICORELibrary/clickhouse/cc_sqlalchemy/__init__.py
AICORELibrary/clickhouse/cc_sqlalchemy/dialect.py
AICORELibrary/clickhouse/cc_sqlalchemy/inspector.py
AICORELibrary/clickhouse/cc_sqlalchemy/datatypes/__init__.py
AICORELibrary/clickhouse/cc_sqlalchemy/datatypes/base.py
AICORELibrary/clickhouse/cc_sqlalchemy/datatypes/sqltypes.py
AICORELibrary/clickhouse/cc_sqlalchemy/ddl/__init__.py
AICORELibrary/clickhouse/cc_sqlalchemy/ddl/custom.py
AICORELibrary/clickhouse/cc_sqlalchemy/ddl/tableengine.py
AICORELibrary/clickhouse/cc_sqlalchemy/sql/__init__.py
AICORELibrary/clickhouse/cc_sqlalchemy/sql/ddlcompiler.py
AICORELibrary/clickhouse/cc_sqlalchemy/sql/preparer.py
AICORELibrary/clickhouse/datatypes/__init__.py
AICORELibrary/clickhouse/datatypes/base.py
AICORELibrary/clickhouse/datatypes/container.py
AICORELibrary/clickhouse/datatypes/format.py
AICORELibrary/clickhouse/datatypes/network.py
AICORELibrary/clickhouse/datatypes/numeric.py
AICORELibrary/clickhouse/datatypes/registry.py
AICORELibrary/clickhouse/datatypes/special.py
AICORELibrary/clickhouse/datatypes/string.py
AICORELibrary/clickhouse/datatypes/temporal.py
AICORELibrary/clickhouse/dbapi/__init__.py
AICORELibrary/clickhouse/dbapi/connection.py
AICORELibrary/clickhouse/dbapi/cursor.py
AICORELibrary/clickhouse/driver/__init__.py
AICORELibrary/clickhouse/driver/buffer.py
AICORELibrary/clickhouse/driver/client.py
AICORELibrary/clickhouse/driver/common.py
AICORELibrary/clickhouse/driver/compression.py
AICORELibrary/clickhouse/driver/constants.py
AICORELibrary/clickhouse/driver/context.py
AICORELibrary/clickhouse/driver/ctypes.py
AICORELibrary/clickhouse/driver/dataconv.py
AICORELibrary/clickhouse/driver/ddl.py
AICORELibrary/clickhouse/driver/errors.py
AICORELibrary/clickhouse/driver/exceptions.py
AICORELibrary-1.0.2.dist-info/METADATA
AICORELibrary-1.0.2.dist-info/WHEEL
AICORELibrary-1.0.2.dist-info/top_level.txt
AICORELibrary-1.0.2.dist-info/RECORD
