Metadata-Version: 2.1
Name: AICORELibrary
Version: 1.0.2
Summary: AI Core Package for AI
Author: IT Dev HOTD Python Developer
Classifier: Programming Language :: Python :: 3
Classifier: License :: OSI Approved :: MIT License
Classifier: Operating System :: OS Independent
Requires-Python: >=3.8
Provides-Extra: arrow
Requires-Dist: pyarrow ; extra == 'arrow'
Provides-Extra: numpy
Requires-Dist: numpy ; extra == 'numpy'
Provides-Extra: orjson
Requires-Dist: orjson ; extra == 'orjson'
Provides-Extra: pandas
Requires-Dist: pandas ; extra == 'pandas'
Provides-Extra: sqlalchemy
Requires-Dist: sqlalchemy ; extra == 'sqlalchemy'
Provides-Extra: tzlocal
Requires-Dist: tzlocal ; extra == 'tzlocal'
